bitflags/__init__.py
bitflags/__meta__.py
bitflags/bitflags.py
bitflags/flag_bits.py
bitflags/utils.py
bitflags-1.2.0.dist-info/METADATA
bitflags-1.2.0.dist-info/WHEEL
bitflags-1.2.0.dist-info/licenses/LICENSE
bitflags-1.2.0.dist-info/RECORD
