Metadata-Version: 2.4
Name: bitflags
Version: 1.2.0
Summary: Bit flags implementation using a C Union. This library removes the need to use ctypes and helps you quickly access what bits are toggled.
Project-URL: Repository, https://github.com/justengel/bitflags.git
Author-email: Justin Engel <jtengel08@gmail.com>
License: MIT License
License-File: LICENSE
Keywords: Union,bit,bitflags,flags
Classifier: Development Status :: 4 - Beta
Classifier: Intended Audience :: Developers
Classifier: License :: OSI Approved :: MIT License
Classifier: Programming Language :: Python :: 3
Classifier: Programming Language :: Python :: 3.13
Classifier: Topic :: Software Development :: Build Tools
Requires-Python: >=3.13
